k8s_diagram/__init__.py
k8s_diagram/app.py
k8s_diagram/diagram.py
k8s_diagram/kinds.py
k8s_diagram/pull_cluster_info.sh
k8s_diagram-0.1.8.dist-info/entry_points.txt
k8s_diagram-0.1.8.dist-info/LICENSE
k8s_diagram-0.1.8.dist-info/WHEEL
k8s_diagram-0.1.8.dist-info/METADATA
k8s_diagram-0.1.8.dist-info/RECORD
