Metadata-Version: 2.1
Name: k8s-diagram
Version: 0.1.8
Summary: Creates a preview diagram of Kubernetes Resources without the need to apply them.
Author: Jimmy Mills
Author-email: jimmyemills+github@gmail.com
Requires-Python: >=3.8.2,<4.0.0
Classifier: Programming Language :: Python :: 3
Classifier: Programming Language :: Python :: 3.9
Requires-Dist: PyYAML (>=5.4.1,<6.0.0)
Requires-Dist: argparse (>=1.4.0,<2.0.0)
Requires-Dist: diagrams (>=0.20.0,<0.21.0)
Requires-Dist: typer[all] (>=0.3.2,<0.4.0)
